PytorchRengongzhinengYantaohuiChuyiFix1/README.md
PytorchRengongzhinengYantaohuiChuyiFix1/__init__.py
PytorchRengongzhinengYantaohuiChuyiFix1/__main__.py
PytorchRengongzhinengYantaohuiChuyiFix1/file.epub
PytorchRengongzhinengYantaohuiChuyiFix1/index.html
PytorchRengongzhinengYantaohuiChuyiFix1/css/__init__.py
PytorchRengongzhinengYantaohuiChuyiFix1/css/annotations.css
PytorchRengongzhinengYantaohuiChuyiFix1/css/main.css
PytorchRengongzhinengYantaohuiChuyiFix1/css/normalize.css
PytorchRengongzhinengYantaohuiChuyiFix1/css/popup.css
PytorchRengongzhinengYantaohuiChuyiFix1/font/__init__.py
PytorchRengongzhinengYantaohuiChuyiFix1/font/fontello.eot
PytorchRengongzhinengYantaohuiChuyiFix1/font/fontello.svg
PytorchRengongzhinengYantaohuiChuyiFix1/font/fontello.ttf
PytorchRengongzhinengYantaohuiChuyiFix1/font/fontello.woff
PytorchRengongzhinengYantaohuiChuyiFix1/img/__init__.py
PytorchRengongzhinengYantaohuiChuyiFix1/img/annotator-glyph-sprite.png
PytorchRengongzhinengYantaohuiChuyiFix1/img/annotator-icon-sprite.png
PytorchRengongzhinengYantaohuiChuyiFix1/img/apple-touch-icon.png
PytorchRengongzhinengYantaohuiChuyiFix1/img/cancelfullscreen.png
PytorchRengongzhinengYantaohuiChuyiFix1/img/close.png
PytorchRengongzhinengYantaohuiChuyiFix1/img/fullscreen.png
PytorchRengongzhinengYantaohuiChuyiFix1/img/loader.gif
PytorchRengongzhinengYantaohuiChuyiFix1/img/menu-icon.png
PytorchRengongzhinengYantaohuiChuyiFix1/img/save.png
PytorchRengongzhinengYantaohuiChuyiFix1/img/saved.png
PytorchRengongzhinengYantaohuiChuyiFix1/img/settings-s.png
PytorchRengongzhinengYantaohuiChuyiFix1/img/settings.png
PytorchRengongzhinengYantaohuiChuyiFix1/img/star.png
PytorchRengongzhinengYantaohuiChuyiFix1/js/__init__.py
PytorchRengongzhinengYantaohuiChuyiFix1/js/epub.js
PytorchRengongzhinengYantaohuiChuyiFix1/js/epub.min.js
PytorchRengongzhinengYantaohuiChuyiFix1/js/epub.min.map
PytorchRengongzhinengYantaohuiChuyiFix1/js/hooks.min.js
PytorchRengongzhinengYantaohuiChuyiFix1/js/hooks.min.map
pytorch_rengongzhineng_yantaohui_chuyi_fix1-2025.3.25.0.dist-info/METADATA
pytorch_rengongzhineng_yantaohui_chuyi_fix1-2025.3.25.0.dist-info/WHEEL
pytorch_rengongzhineng_yantaohui_chuyi_fix1-2025.3.25.0.dist-info/entry_points.txt
pytorch_rengongzhineng_yantaohui_chuyi_fix1-2025.3.25.0.dist-info/top_level.txt
pytorch_rengongzhineng_yantaohui_chuyi_fix1-2025.3.25.0.dist-info/RECORD
